shardcomputer.cpython-310-aarch64-linux-gnu.so
shard_computer-1.2.2.dist-info/LICENSE
shard_computer-1.2.2.dist-info/WHEEL
shard_computer-1.2.2.dist-info/RECORD
shard_computer-1.2.2.dist-info/top_level.txt
shard_computer-1.2.2.dist-info/METADATA
