Metadata-Version: 2.2
Name: shard-computer
Version: 1.2.2
Summary: A library for rapid computation of Neuroglancer Precomputed shard hashes.
Home-page: https://github.com/seung-lab/shard-computer/
Author: William Silversmith
Author-email: ws9@princeton.edu
License: License :: OSI Approved :: GNU Lesser General Public License v2 or later (LGPLv2+)
Keywords: neuroglancer sharding igneous cloud-volume MurmurHash3
Classifier: Intended Audience :: Developers
Classifier: Development Status :: 4 - Beta
Classifier: License :: OSI Approved :: BSD License
Classifier: Programming Language :: Python
Classifier: Programming Language :: Python :: 3
Classifier: Programming Language :: Python :: 3.9
Classifier: Programming Language :: Python :: 3.10
Classifier: Programming Language :: Python :: 3.11
Classifier: Programming Language :: Python :: 3.12
Classifier: Programming Language :: Python :: 3.13
Classifier: Topic :: Scientific/Engineering
Classifier: Intended Audience :: Science/Research
Classifier: Operating System :: POSIX
Classifier: Operating System :: MacOS
Classifier: Operating System :: Microsoft :: Windows :: Windows 10
Classifier: Topic :: Utilities
Requires-Python: >=3.8.0,<4.0.0
License-File: LICENSE
Dynamic: author
Dynamic: author-email
Dynamic: classifier
Dynamic: description
Dynamic: description-content-type
Dynamic: home-page
Dynamic: keywords
Dynamic: license
Dynamic: requires-python
Dynamic: summary
